test_lightform_demo_package/__init__.py
test_lightform_demo_package/_version.py
test_lightform_demo_package/main.py
test_lightform_demo_package-0.1.0.dist-info/METADATA
test_lightform_demo_package-0.1.0.dist-info/WHEEL
test_lightform_demo_package-0.1.0.dist-info/top_level.txt
test_lightform_demo_package-0.1.0.dist-info/RECORD
